{
  "skill_id": "rhetoric-of-decks",
  "display_name": "rhetoric-of-decks",
  "skill_path": "rhetoric-of-decks",
  "source_type": "local-created",
  "source": "",
  "source_url": "",
  "ref": "",
  "subpath": "",
  "bootstrap": true,
  "upstream_enabled": false,
  "upstream_path": ".skills/upstream/rhetoric-of-decks",
  "last_imported_at": "2026-04-07T17:04:29Z",
  "upstream_revision": "",
  "managed_revision": "sha256:2224d7112c79f55abcbf9a85039517a8777d45a0cfe5ecade1efa654bfca50f2",
  "managed_dirty": false
}
